{
  "HeWeather5": [
    {
      "aqi": {
        "city": {
          "aqi": "256",
          "co": "4",
          "no2": "85",
          "o3": "2",
          "pm10": "164",
          "pm25": "256",
          "qlty": "重度污染",
          "so2": "9"
        }
      },
      "basic": {
        "city": "北京",
        "cnty": "中国",
        "id": "CN101010100",
        "lat": "39.904000",
        "lon": "116.391000",
        "update": {
          "loc": "2016-11-18 19:53",
          "utc": "2016-11-18 11:53"
        }
      },
      "daily_forecast": [
        {
          "astro": {
            "mr": "20:51",
            "ms": "10:34",
            "sr": "07:03",
            "ss": "16:56"
          },
          "cond": {
            "code_d": "103",
            "code_n": "502",
            "txt_d": "晴间多云",
            "txt_n": "霾"
          },
          "date": "2016-11-18",
          "hum": "83",
          "pcpn": "0.0",
          "pop": "0",
          "pres": "1015",
          "tmp": {
            "max": "10",
            "min": "5"
          },
          "uv": "2",
          "vis": "10",
          "wind": {
            "deg": "123",
            "dir": "无持续风向",
            "sc": "微风",
            "spd": "10"
          }
        },
        {
          "astro": {
            "mr": "21:55",
            "ms": "11:26",
            "sr": "07:04",
            "ss": "16:55"
          },
          "cond": {
            "code_d": "101",
            "code_n": "305",
            "txt_d": "多云",
            "txt_n": "小雨"
          },
          "date": "2016-11-19",
          "hum": "42",
          "pcpn": "0.0",
          "pop": "0",
          "pres": "1018",
          "tmp": {
            "max": "13",
            "min": "3"
          },
          "uv": "2",
          "vis": "10",
          "wind": {
            "deg": "324",
            "dir": "无持续风向",
            "sc": "微风",
            "spd": "9"
          }
        },
        {
          "astro": {
            "mr": "22:57",
            "ms": "12:09",
            "sr": "07:05",
            "ss": "16:54"
          },
          "cond": {
            "code_d": "404",
            "code_n": "402",
            "txt_d": "雨夹雪",
            "txt_n": "大雪"
          },
          "date": "2016-11-20",
          "hum": "52",
          "pcpn": "4.9",
          "pop": "76",
          "pres": "1027",
          "tmp": {
            "max": "4",
            "min": "0"
          },
          "uv": "2",
          "vis": "9",
          "wind": {
            "deg": "116",
            "dir": "无持续风向",
            "sc": "微风",
            "spd": "3"
          }
        },
        {
          "astro": {
            "mr": "23:59",
            "ms": "12:48",
            "sr": "07:06",
            "ss": "16:54"
          },
          "cond": {
            "code_d": "400",
            "code_n": "104",
            "txt_d": "小雪",
            "txt_n": "阴"
          },
          "date": "2016-11-21",
          "hum": "91",
          "pcpn": "13.3",
          "pop": "100",
          "pres": "1031",
          "tmp": {
            "max": "-1",
            "min": "-5"
          },
          "uv": "1",
          "vis": "2",
          "wind": {
            "deg": "46",
            "dir": "北风",
            "sc": "3-4",
            "spd": "15"
          }
        },
        {
          "astro": {
            "mr": "null",
            "ms": "13:22",
            "sr": "07:07",
            "ss": "16:53"
          },
          "cond": {
            "code_d": "100",
            "code_n": "100",
            "txt_d": "晴",
            "txt_n": "晴"
          },
          "date": "2016-11-22",
          "hum": "79",
          "pcpn": "0.0",
          "pop": "1",
          "pres": "1041",
          "tmp": {
            "max": "-3",
            "min": "-7"
          },
          "uv": "2",
          "vis": "10",
          "wind": {
            "deg": "350",
            "dir": "北风",
            "sc": "3-4",
            "spd": "15"
          }
        },
        {
          "astro": {
            "mr": "00:58",
            "ms": "13:53",
            "sr": "07:08",
            "ss": "16:53"
          },
          "cond": {
            "code_d": "100",
            "code_n": "101",
            "txt_d": "晴",
            "txt_n": "多云"
          },
          "date": "2016-11-23",
          "hum": "77",
          "pcpn": "0.0",
          "pop": "0",
          "pres": "1039",
          "tmp": {
            "max": "-3",
            "min": "-10"
          },
          "uv": "-999",
          "vis": "10",
          "wind": {
            "deg": "288",
            "dir": "无持续风向",
            "sc": "微风",
            "spd": "6"
          }
        },
        {
          "astro": {
            "mr": "01:56",
            "ms": "14:22",
            "sr": "07:09",
            "ss": "16:52"
          },
          "cond": {
            "code_d": "100",
            "code_n": "100",
            "txt_d": "晴",
            "txt_n": "晴"
          },
          "date": "2016-11-24",
          "hum": "75",
          "pcpn": "0.0",
          "pop": "0",
          "pres": "1033",
          "tmp": {
            "max": "-1",
            "min": "-9"
          },
          "uv": "-999",
          "vis": "10",
          "wind": {
            "deg": "180",
            "dir": "无持续风向",
            "sc": "微风",
            "spd": "9"
          }
        }
      ],
      "hourly_forecast": [
        {
          "cond": {
            "code": "502",
            "txt": "霾"
          },
          "date": "2016-11-18 22:00",
          "hum": "88",
          "pop": "0",
          "pres": "1013",
          "tmp": "7",
          "wind": {
            "deg": "241",
            "dir": "无持续风向",
            "sc": "微风",
            "spd": "6"
          }
        }
      ],
      "now": {
        "cond": {
          "code": "502",
          "txt": "霾"
        },
        "fl": "7",
        "hum": "95",
        "pcpn": "0",
        "pres": "1013",
        "tmp": "6",
        "vis": "1",
        "wind": {
          "deg": "30",
          "dir": "东北风",
          "sc": "3-4",
          "spd": "14"
        }
      },
      "status": "ok",
      "suggestion": {
        "air": {
          "brf": "较差",
          "txt": "气象条件较不利于空气污染物扩散。"
        },
        "comf": {
          "brf": "较舒适",
          "txt": "白天天气晴好，早晚会感觉偏凉，午后舒适、宜人。"
        },
        "cw": {
          "brf": "不宜",
          "txt": "不宜洗车，未来24小时内有霾，如果在此期间洗车，会弄脏您的爱车。"
        },
        "drsg": {
          "brf": "较冷",
          "txt": "建议着厚外套加毛衣等服装。年老体弱者宜着大衣、呢外套加羊毛衫。"
        },
        "flu": {
          "brf": "较易发",
          "txt": "昼夜温差较大，较易发生感冒，请适当增减衣服。体质较弱的朋友请注意防护。"
        },
        "sport": {
          "brf": "较适宜",
          "txt": "天气较好，但风力较大，推荐您进行室内运动，若在户外运动请注意避风保暖。"
        },
        "trav": {
          "brf": "适宜",
          "txt": "天气较好，温度适宜，但风稍微有点大。这样的天气适宜旅游，您可以尽情地享受大自然的无限风光。"
        },
        "uv": {
          "brf": "最弱",
          "txt": "属弱紫外线辐射天气，无需特别防护。若长期在户外，建议涂擦SPF在8-12之间的防晒护肤品。"
        }
      }
    }
  ]
}
